SDStools/__init__.py
SDStools/linkedlist/LinkList.py
SDStools/linkedlist/SinCycLinkList.py
SDStools/linkedlist/TwoWayLinkList.py
SDStools/linkedlist/__init__.py
SDStools/tree/BinaryTree.py
SDStools/tree/__init__.py
SDStools-0.1.7.dist-info/DESCRIPTION.rst
SDStools-0.1.7.dist-info/METADATA
SDStools-0.1.7.dist-info/RECORD
SDStools-0.1.7.dist-info/WHEEL
SDStools-0.1.7.dist-info/metadata.json
SDStools-0.1.7.dist-info/top_level.txt
