Metadata-Version: 2.0
Name: SDStools
Version: 0.1.7
Summary: Senior Data Structure Tools.
Home-page: https://github.com/shubihu/SDStools
Author: Yahaha
Author-email: jrwjb@sina.com
License: MIT
Platform: UNKNOWN
Classifier: License :: OSI Approved :: MIT License
Classifier: Programming Language :: Python
Classifier: Programming Language :: Python :: 3
Classifier: Programming Language :: Python :: 3.6
Classifier: Programming Language :: Python :: Implementation :: CPython
Classifier: Programming Language :: Python :: Implementation :: PyPy
Requires-Python: >=3.6.0
